{
  "meta": {
    "promotion": 3
  },
  "assets": {
    "WID_Firework_Gun": {
      "meta": {
        "revision": 3,
        "headRevision": 3,
        "revisedAt": "2022-06-23T19:53:18.811Z",
        "promotion": 3,
        "promotedAt": "2022-06-28T13:02:33.229Z"
      },
      "assetData": {
        "primaryAssetId": "Weapon:WID_Firework_Gun",
        "CreativeTagsHelper": {
          "CreativeTags": [
            "FireStarting",
            "Weapon",
            "Rare",
            "Ammo:Special",
            "RecentlyAdded",
            "NewThisSeason",
            "Vibin"
          ]
        }
      }
    },
    "WID_Sawblade_Athena": {
      "meta": {
        "revision": 2,
        "headRevision": 2,
        "revisedAt": "2022-06-10T13:47:11.735Z",
        "promotion": 2,
        "promotedAt": "2022-06-28T13:02:02.487Z"
      },
      "assetData": {
        "primaryAssetId": "Weapon:WID_Sawblade_Athena",
        "CreativeTagsHelper": {
          "CreativeTags": [
            "Vibin",
            "RecentlyAdded",
            "NewThisSeason",
            "Ammo:Special",
            "Rare",
            "Weapon"
          ]
        }
      }
    }
  }
}